{"stats":{"minecraft:custom":{"minecraft:animals_bred":2,"minecraft:interact_with_crafting_table":232,"minecraft:open_barrel":3,"minecraft:leave_game":94,"minecraft:time_since_death":373426,"minecraft:sprint_one_cm":5691562,"minecraft:damage_blocked_by_shield":6245,"minecraft:drop":140,"minecraft:talked_to_villager":84,"minecraft:deaths":20,"minecraft:jump":38774,"minecraft:walk_on_water_one_cm":618805,"minecraft:enchant_item":5,"minecraft:interact_with_furnace":1118,"minecraft:play_record":1,"minecraft:traded_with_villager":32,"minecraft:play_one_minute":2922530,"minecraft:interact_with_loom":2,"minecraft:sleep_in_bed":35,"minecraft:damage_dealt":66553,"minecraft:player_kills":3,"minecraft:crouch_one_cm":924286,"minecraft:interact_with_smoker":1,"minecraft:inspect_dropper":1,"minecraft:interact_with_anvil":7,"minecraft:mob_kills":1204,"minecraft:fill_cauldron":2,"minecraft:climb_one_cm":246448,"minecraft:walk_one_cm":6345421,"minecraft:raid_win":1,"minecraft:sneak_time":257848,"minecraft:walk_under_water_one_cm":1953568,"minecraft:boat_one_cm":1785295,"minecraft:interact_with_lectern":1,"minecraft:time_since_rest":373452,"minecraft:damage_taken":13716,"minecraft:minecart_one_cm":291673,"minecraft:swim_one_cm":1057935,"minecraft:fly_one_cm":26817812,"minecraft:open_chest":1095,"minecraft:aviate_one_cm":7630115,"minecraft:fall_one_cm":511480},"minecraft:dropped":{"minecraft:gold_ore":12,"minecraft:iron_sword":1,"minecraft:lapis_lazuli":25,"minecraft:baked_potato":29,"minecraft:cooked_porkchop":2,"minecraft:dark_oak_slab":1,"minecraft:crossbow":1,"minecraft:lantern":1,"minecraft:leather":1,"minecraft:rail":2,"minecraft:leather_helmet":1,"minecraft:structure_void":5,"minecraft:dirt":27,"minecraft:iron_pickaxe":2,"minecraft:pink_glazed_terracotta":1,"minecraft:white_wool":4,"minecraft:gold_ingot":1,"minecraft:bone":9,"minecraft:gravel":57,"minecraft:sugar_cane":2,"minecraft:obsidian":1,"minecraft:rotten_flesh":8,"minecraft:oak_planks":57,"minecraft:white_bed":5,"minecraft:iron_ore":2,"minecraft:arrow":6,"minecraft:powered_rail":2,"minecraft:stone_brick_stairs":64,"minecraft:egg":1,"minecraft:bread":65,"minecraft:wheat_seeds":902,"minecraft:diamond_leggings":1,"minecraft:poisonous_potato":2,"minecraft:cobblestone":562,"minecraft:iron_helmet":1,"minecraft:feather":2,"minecraft:granite":58,"minecraft:milk_bucket":1,"minecraft:diorite":94,"minecraft:yellow_shulker_box":3,"minecraft:diamond_helmet":1,"minecraft:iron_leggings":3,"minecraft:iron_axe":1,"minecraft:redstone_block":2,"minecraft:kelp":2,"minecraft:brown_stained_glass_pane":7,"minecraft:light_gray_wool":2,"minecraft:iron_boots":3,"minecraft:diamond_sword":4,"minecraft:shield":1,"minecraft:diamond_chestplate":2,"minecraft:iron_chestplate":4,"minecraft:diamond_pickaxe":1,"minecraft:andesite":28,"minecraft:spider_eye":1,"minecraft:diamond_boots":1,"minecraft:wooden_pickaxe":1,"minecraft:magma_block":1},"minecraft:broken":{"minecraft:stone_pickaxe":16,"minecraft:diamond_pickaxe":1,"minecraft:iron_sword":3,"minecraft:stone_hoe":1,"minecraft:shield":1,"minecraft:iron_axe":3,"minecraft:iron_pickaxe":32,"minecraft:iron_helmet":2},"minecraft:mined":{"minecraft:white_bed":10,"minecraft:farmland":3,"minecraft:cobblestone_stairs":35,"minecraft:obsidian":1,"minecraft:granite":258,"minecraft:grass_block":78,"minecraft:frosted_ice":3,"minecraft:oak_wall_sign":2,"minecraft:magma_block":1,"minecraft:iron_ore":1010,"minecraft:kelp_plant":1,"minecraft:torch":189,"minecraft:chest":43,"minecraft:spruce_wall_sign":1,"minecraft:cobblestone":427,"minecraft:sugar_cane":177,"minecraft:oak_planks":320,"minecraft:wall_torch":77,"minecraft:dark_oak_slab":1,"minecraft:wheat":924,"minecraft:stone_brick_stairs":156,"minecraft:smooth_stone_slab":88,"minecraft:grass":164,"minecraft:oak_log":446,"minecraft:sand":14,"minecraft:dirt":215,"minecraft:oak_leaves":85,"minecraft:diamond_ore":43,"minecraft:ladder":104,"minecraft:spruce_leaves":17,"minecraft:kelp":9,"minecraft:redstone_ore":32,"minecraft:oak_trapdoor":7,"minecraft:furnace":23,"minecraft:andesite":307,"minecraft:potatoes":58,"minecraft:stone":5963,"minecraft:oak_slab":16,"minecraft:stone_brick_slab":383,"minecraft:crafting_table":15,"minecraft:stone_slab":69,"minecraft:lapis_ore":29,"minecraft:diorite":334,"minecraft:birch_planks":3,"minecraft:brick_slab":29,"minecraft:sweet_berry_bush":568,"minecraft:spruce_log":7,"minecraft:coal_ore":1576,"minecraft:gravel":53,"minecraft:cobweb":14,"minecraft:stone_bricks":1054,"minecraft:gold_ore":42},"minecraft:killed_by":{"minecraft:creeper":3,"minecraft:pillager":1,"minecraft:ravager":1,"minecraft:witch":1,"minecraft:player":1,"minecraft:skeleton":2},"minecraft:killed":{"minecraft:cave_spider":7,"minecraft:witch":1,"minecraft:spider":14,"minecraft:cod":20,"minecraft:skeleton":63,"minecraft:fox":1,"minecraft:chicken":120,"minecraft:cat":47,"minecraft:pig":5,"minecraft:salmon":5,"minecraft:iron_golem":2,"minecraft:creeper":22,"minecraft:sheep":553,"minecraft:trader_llama":2,"minecraft:pillager":20,"minecraft:zombie":235,"minecraft:cow":16,"minecraft:evoker":1,"minecraft:vindicator":3,"minecraft:llama":10,"minecraft:drowned":7,"minecraft:ocelot":4,"minecraft:wandering_trader":1,"minecraft:polar_bear":10},"minecraft:picked_up":{"minecraft:iron_chestplate":13,"minecraft:wheat":990,"minecraft:redstone_block":2,"minecraft:stone_slab":101,"minecraft:lead":4,"minecraft:diamond_sword":4,"minecraft:oak_stairs":14,"minecraft:potion":1,"minecraft:enchanted_book":1,"minecraft:stone_brick_stairs":252,"minecraft:string":100,"minecraft:smooth_stone_slab":115,"minecraft:iron_leggings":11,"minecraft:pufferfish":4,"minecraft:oak_sign":3,"minecraft:diamond_leggings":2,"minecraft:bucket":2,"minecraft:spruce_planks":12,"minecraft:iron_pickaxe":17,"minecraft:iron_boots":11,"minecraft:furnace":23,"minecraft:golden_helmet":3,"minecraft:stick":35,"minecraft:composter":1,"minecraft:oak_fence":3,"minecraft:torch":1153,"minecraft:spruce_stairs":6,"minecraft:porkchop":8,"minecraft:diorite":594,"minecraft:golden_chestplate":3,"minecraft:yellow_banner":1,"minecraft:stone_sword":2,"minecraft:rotten_flesh":326,"minecraft:obsidian":1,"minecraft:cod":21,"minecraft:cobblestone":12914,"minecraft:magma_block":1,"minecraft:feather":127,"minecraft:cooked_beef":2,"minecraft:repeater":5,"minecraft:andesite":642,"minecraft:brown_wool":1,"minecraft:potato":219,"minecraft:flint":12,"minecraft:lantern":26,"minecraft:lapis_lazuli":329,"minecraft:dirt":532,"minecraft:name_tag":1,"minecraft:leather_boots":1,"minecraft:bone":142,"minecraft:bow":7,"minecraft:wheat_seeds":3068,"minecraft:diamond_helmet":2,"minecraft:powered_rail":2,"minecraft:stone_hoe":1,"minecraft:oak_planks":559,"minecraft:cooked_porkchop":6,"minecraft:oak_pressure_plate":1,"minecraft:poisonous_potato":2,"minecraft:sand":30,"minecraft:iron_hoe":3,"minecraft:diamond":166,"minecraft:crossbow":4,"minecraft:granite":466,"minecraft:bone_meal":36,"minecraft:spruce_sign":1,"minecraft:emerald":4,"minecraft:bread":346,"minecraft:oak_sapling":48,"minecraft:netherrack":1,"minecraft:diamond_pickaxe":7,"minecraft:fishing_rod":1,"minecraft:crafting_table":17,"minecraft:splash_potion":1,"minecraft:chicken":114,"minecraft:ladder":139,"minecraft:brown_mushroom":2,"minecraft:shield":9,"minecraft:oak_trapdoor":21,"minecraft:iron_axe":2,"minecraft:iron_shovel":7,"minecraft:magenta_wool":2,"minecraft:brown_stained_glass_pane":7,"minecraft:beef":31,"minecraft:oak_boat":10,"minecraft:poppy":2,"minecraft:light_gray_wool":3,"minecraft:minecart":4,"minecraft:sugar_cane":365,"minecraft:chest":67,"minecraft:birch_sapling":6,"minecraft:egg":220,"minecraft:stone":321,"minecraft:oak_door":4,"minecraft:stone_button":2,"minecraft:music_disc_11":16,"minecraft:redstone":234,"minecraft:stone_pressure_plate":2,"minecraft:arrow":134,"minecraft:diamond_chestplate":3,"minecraft:beetroot_seeds":8,"minecraft:pink_glazed_terracotta":1,"minecraft:tube_coral_fan":1,"minecraft:shears":2,"minecraft:diamond_boots":2,"minecraft:totem_of_undying":3,"minecraft:saddle":1,"minecraft:black_banner":9,"minecraft:gold_ingot":14,"minecraft:mutton":51,"minecraft:rail":27,"minecraft:white_wool":76,"minecraft:yellow_shulker_box":3,"minecraft:salmon":4,"minecraft:leather":19,"minecraft:music_disc_stal":1,"minecraft:red_mushroom":5,"minecraft:filled_map":2,"minecraft:birch_planks":62,"minecraft:oak_log":445,"minecraft:golden_boots":3,"minecraft:gunpowder":39,"minecraft:cobblestone_stairs":62,"minecraft:white_banner":10,"minecraft:apple":4,"minecraft:stone_bricks":1034,"minecraft:kelp":85,"minecraft:iron_ingot":10,"minecraft:stone_pickaxe":3,"minecraft:iron_ore":1371,"minecraft:iron_sword":15,"minecraft:oak_slab":10,"minecraft:milk_bucket":1,"minecraft:dark_oak_slab":2,"minecraft:birch_boat":3,"minecraft:sweet_berries":2063,"minecraft:yellow_concrete":16,"minecraft:stone_brick_slab":461,"minecraft:gravel":170,"minecraft:spruce_sapling":9,"minecraft:white_bed":11,"minecraft:spruce_log":8,"minecraft:gold_ore":83,"minecraft:mossy_stone_brick_slab":1,"minecraft:spider_eye":25,"minecraft:leather_helmet":5,"minecraft:brick_slab":58,"minecraft:firework_rocket":31,"minecraft:pumpkin_seeds":4,"minecraft:stone_axe":3,"minecraft:chainmail_leggings":2,"minecraft:iron_helmet":7,"minecraft:gray_wool":2,"minecraft:baked_potato":29,"minecraft:coal":3884},"minecraft:crafted":{"minecraft:oak_planks":1120,"minecraft:smooth_stone":570,"minecraft:oak_sign":36,"minecraft:cooked_chicken":2,"minecraft:stone":8983,"minecraft:cobblestone_stairs":4,"minecraft:stone_brick_slab":2970,"minecraft:bow":4,"minecraft:diamond_helmet":1,"minecraft:diamond_leggings":1,"minecraft:iron_boots":4,"minecraft:chest":33,"minecraft:stone_hoe":2,"minecraft:stone_bricks":8112,"minecraft:oak_fence":3,"minecraft:golden_boots":1,"minecraft:oak_slab":6,"minecraft:emerald":31,"minecraft:cooked_porkchop":4,"minecraft:crafting_table":4,"minecraft:spruce_planks":32,"minecraft:wooden_pickaxe":1,"minecraft:iron_helmet":4,"minecraft:stone_brick_stairs":664,"minecraft:iron_chestplate":5,"minecraft:book":14,"minecraft:paper":273,"minecraft:diamond_pickaxe":2,"minecraft:shield":5,"minecraft:stick":680,"minecraft:stone_slab":852,"minecraft:iron_ingot":1421,"minecraft:iron_pickaxe":36,"minecraft:iron_block":59,"minecraft:stone_sword":1,"minecraft:gold_ingot":14,"minecraft:shears":1,"minecraft:oak_door":3,"minecraft:smooth_stone_slab":1140,"minecraft:furnace":24,"minecraft:bone_meal":3,"minecraft:oak_trapdoor":134,"minecraft:diamond":9,"minecraft:iron_axe":6,"minecraft:ladder":156,"minecraft:iron_hoe":2,"minecraft:stone_pickaxe":18,"minecraft:diamond_boots":1,"minecraft:golden_helmet":1,"minecraft:minecart":1,"minecraft:diamond_sword":1,"minecraft:iron_sword":7,"minecraft:bucket":2,"minecraft:stone_axe":1,"minecraft:enchanted_book":1,"minecraft:bread":225,"minecraft:air":0,"minecraft:oak_boat":5,"minecraft:oak_stairs":16,"minecraft:iron_shovel":1,"minecraft:iron_leggings":4,"minecraft:white_bed":5,"minecraft:torch":656,"minecraft:diamond_chestplate":1},"minecraft:used":{"minecraft:jack_o_lantern":2,"minecraft:iron_shovel":183,"minecraft:ladder":286,"minecraft:bone_block":4,"minecraft:oak_sign":88,"minecraft:white_concrete_powder":3,"minecraft:chest":209,"minecraft:stone":7600,"minecraft:brown_concrete":14,"minecraft:iron_sword":1289,"minecraft:bubble_coral":16,"minecraft:grass":100,"minecraft:rotten_flesh":64,"minecraft:milk_bucket":12,"minecraft:obsidian":90,"minecraft:spruce_boat":2,"minecraft:grass_block":625,"minecraft:lantern":79,"minecraft:dark_oak_wood":294,"minecraft:pink_wool":6192,"minecraft:stone_brick_stairs":1305,"minecraft:stone_bricks":6868,"minecraft:music_disc_stal":1,"minecraft:bedrock":35,"minecraft:birch_trapdoor":1,"minecraft:repeater":16,"minecraft:bow":50,"minecraft:dark_oak_boat":1,"minecraft:sweet_berries":1386,"minecraft:furnace":43,"minecraft:egg":136,"minecraft:potato":59,"minecraft:emerald_ore":3,"minecraft:dark_oak_stairs":4,"minecraft:diorite":67,"minecraft:stone_pickaxe":2227,"minecraft:dark_oak_sign":5,"minecraft:oak_planks":321,"minecraft:polished_diorite_slab":66,"minecraft:wooden_pickaxe":19,"minecraft:fox_spawn_egg":1,"minecraft:composter":4,"minecraft:clay":4,"minecraft:sugar_cane":83,"minecraft:white_wool":8,"minecraft:jungle_boat":1,"minecraft:oak_leaves":9,"minecraft:brain_coral":22,"minecraft:dark_oak_trapdoor":7,"minecraft:sand":201,"minecraft:yellow_terracotta":2,"minecraft:loom":1,"minecraft:blast_furnace":1,"minecraft:black_banner":140,"minecraft:light_gray_terracotta":3,"minecraft:yellow_concrete":20,"minecraft:crossbow":1,"minecraft:sponge":115,"minecraft:stone_brick_wall":70,"minecraft:gray_concrete":150,"minecraft:creeper_spawn_egg":152,"minecraft:redstone_torch":2,"minecraft:firework_rocket":8,"minecraft:black_concrete":327,"minecraft:stone_button":7,"minecraft:dark_oak_log":169,"minecraft:birch_slab":288,"minecraft:bread":171,"minecraft:barrier":2,"minecraft:oak_pressure_plate":45,"minecraft:diamond_ore":6,"minecraft:gravel":196,"minecraft:diamond_sword":169,"minecraft:coal_block":8,"minecraft:bubble_coral_block":57,"minecraft:grindstone":2,"minecraft:dark_oak_fence":40,"minecraft:smithing_table":2,"minecraft:white_stained_glass":58,"minecraft:green_concrete_powder":2,"minecraft:andesite":203,"minecraft:pink_stained_glass":1,"minecraft:smooth_stone_slab":1256,"minecraft:oak_boat":18,"minecraft:bone_meal":3,"minecraft:experience_bottle":1,"minecraft:oak_fence":23,"minecraft:oak_trapdoor":143,"minecraft:enchanting_table":1,"minecraft:stone_sword":23,"minecraft:brain_coral_fan":17,"minecraft:flint_and_steel":292,"minecraft:redstone":115,"minecraft:silverfish_spawn_egg":228,"minecraft:spruce_planks":45,"minecraft:stone_hoe":251,"minecraft:cooked_chicken":2,"minecraft:netherrack":1,"minecraft:oak_door":5,"minecraft:torch":1177,"minecraft:brewing_stand":2,"minecraft:dirt":469,"minecraft:anvil":4,"minecraft:spruce_stairs":126,"minecraft:cobblestone_wall":64,"minecraft:polished_granite_slab":31,"minecraft:dead_brain_coral_block":4,"minecraft:granite":50,"minecraft:polished_diorite":56,"minecraft:iron_hoe":209,"minecraft:stone_brick_slab":4075,"minecraft:brown_terracotta":70,"minecraft:dark_oak_planks":5,"minecraft:bookshelf":38,"minecraft:iron_axe":948,"minecraft:oak_stairs":2,"minecraft:smooth_quartz":1,"minecraft:barrel":8,"minecraft:tall_grass":413,"minecraft:beef":1,"minecraft:iron_trapdoor":2,"minecraft:podzol":38,"minecraft:minecart":3,"minecraft:brain_coral_block":59,"minecraft:wheat_seeds":1369,"minecraft:yellow_banner":79,"minecraft:acacia_boat":1,"minecraft:water_bucket":110,"minecraft:iron_ore":4,"minecraft:jigsaw":1,"minecraft:cobblestone_stairs":247,"minecraft:snow_block":32,"minecraft:birch_planks":1,"minecraft:lime_wool":1,"minecraft:cartography_table":1,"minecraft:bubble_coral_fan":19,"minecraft:birch_boat":4,"minecraft:brown_mushroom":4,"minecraft:red_mushroom_block":5,"minecraft:spruce_sign":1,"minecraft:cauldron":2,"minecraft:beacon":2,"minecraft:fletching_table":1,"minecraft:stonecutter":4,"minecraft:cobblestone_slab":177,"minecraft:horse_spawn_egg":1,"minecraft:pink_concrete":1,"minecraft:stripped_dark_oak_log":1,"minecraft:terracotta":208,"minecraft:vine":106,"minecraft:tnt":1218,"minecraft:oak_slab":16,"minecraft:crafting_table":20,"minecraft:red_mushroom":3,"minecraft:birch_sign":2,"minecraft:white_bed":11,"minecraft:smoker":1,"minecraft:oak_log":97,"minecraft:diamond_pickaxe":1410,"minecraft:apple":4,"minecraft:iron_pickaxe":8312,"minecraft:stone_slab":944,"minecraft:spruce_trapdoor":18,"minecraft:stone_axe":12,"minecraft:magenta_banner":1,"minecraft:fishing_rod":2,"minecraft:cobblestone":3714,"minecraft:potion":1,"minecraft:white_banner":2,"minecraft:cooked_porkchop":8,"minecraft:red_banner":19,"minecraft:bucket":48,"minecraft:sea_pickle":12,"minecraft:kelp":2,"minecraft:splash_potion":1102,"minecraft:smooth_stone":86}},"DataVersion":2230}